<?xml version="1.0"?>
<Results version="1.0">
<ReportNode type="testrun">
<ReportNode type="Action">
<ReportNode type="Step">
<Data>
    <Name>SystemUtil.Run "chrome.exe",1</Name>
    <StartTime>2022-07-05 16:33:00</StartTime>
    <Result>Done</Result>
    <Extension>
      <IconKey>322162a2b2e247f3b0f36a81ec016946</IconKey>
      <IsPlainTextNodeName>True</IsPlainTextNodeName>
    </Extension>
    <DeviceInfo />
  </Data>
</ReportNode>
<ReportNode type="Step">
<Data>
    <Name>Type mismatch: 'Filter_TC0010'</Name>
    <ErrorText>Type mismatch: 'Filter_TC0010'</ErrorText>
    <Description>&lt;BR/&gt;Line (19): &amp;quot;Filter_TC0010()&amp;quot;.</Description>
    <StartTime>2022-07-05 16:33:00</StartTime>
    <Result>Failed</Result>
    <Extension>
      <StackTrace>
        <StackFrame>
          <ModuleName><![CDATA[Action1]]></ModuleName>
          <FileName><![CDATA[Action1]]></FileName>
          <Language><![CDATA[VBScript - script block]]></Language>
          <FunctionName><![CDATA[VBScript global code]]></FunctionName>
          <Scripts><![CDATA[Filter_TC0010()]]></Scripts>
          <LineNo><![CDATA[19]]></LineNo>
        </StackFrame>
      </StackTrace>
      <IconKey>cd36fc0e688841f2abe0ad32e8d99315</IconKey>
      <IsPlainTextNodeName>True</IsPlainTextNodeName>
      <MergeIsErrorIcon>True</MergeIsErrorIcon>
    </Extension>
    <Snapshot reference="Resources\Snapshots\4a025f10-6500-4621-a70c-18d40d129e9c.jpeg" />
    <DeviceInfo />
  </Data>
</ReportNode>
<ReportNode type="Step">
<Data>
    <Name>Stop Run</Name>
    <Description>Run stopped by user.</Description>
    <StartTime>2022-07-05 16:33:14</StartTime>
    <Result>Information</Result>
    <Extension>
      <IconKey>fb7559153336433d944c2bf600a8fa09</IconKey>
      <IsPlainTextNodeName>True</IsPlainTextNodeName>
    </Extension>
  </Data>
</ReportNode>
<Data>
    <Name>Action1</Name>
    <Description />
    <StartTime>2022-07-05 16:32:59</StartTime>
    <Duration>15</Duration>
    <Result>Failed</Result>
    <InputParameters />
    <Extension>
      <IconKey>041d14a8443146b7a52ebbcc15be8793</IconKey>
      <IsPlainTextNodeName>True</IsPlainTextNodeName>
    </Extension>
  </Data>
</ReportNode>
<Data>
    <Name>Driver</Name>
    <ToolName>Micro Focus UFT One</ToolName>
    <ToolVersion>2021</ToolVersion>
    <ToolVersionStringLiteral>2021</ToolVersionStringLiteral>
    <Description />
    <StartTime>2022-07-05 16:32:54</StartTime>
    <Duration>20</Duration>
    <Result>Failed</Result>
    <InputParameters />
    <Extension>
      <IconKey>bc6db1e612194e228ee23a03150e6506</IconKey>
      <IsPlainTextNodeName>True</IsPlainTextNodeName>
    </Extension>
    <Environment>
      <Timezone>+05:30:00</Timezone>
      <Locale>English (United States)</Locale>
      <User>ALCHEMYCLOUD\user249</User>
      <CpuInfo>Intel(R) Xeon(R) CPU E5-2673 v4 @ 2.30GHz</CpuInfo>
      <NumberOfCores>4</NumberOfCores>
      <TotalMemory>16383</TotalMemory>
      <HostName>alchemycloud.co.in\UFT-41</HostName>
      <OSInfo>Windows 10 1703 (x64)</OSInfo>
    </Environment>
    <TestedApplications />
    <Links>
      <Link type="DataTable" reference="Default.xlsx" displayname="Default Data Table" />
    </Links>
  </Data>
</ReportNode>
<GeneralInfo>
    <ResultName>Res22</ResultName>
    <RunStartTime>2022-07-05 16:32:54</RunStartTime>
    <Timezone>+05:30:00</Timezone>
    <OrchestrationToolName>Micro Focus UFT One</OrchestrationToolName>
    <OrchestrationToolVersion>2021</OrchestrationToolVersion>
    <OrchestrationToolVersionStringLiteral>2021</OrchestrationToolVersionStringLiteral>
  </GeneralInfo>
</Results>